quilt/__init__.py
quilt/config.py
quilt/context_base/__init__.py
quilt/context_base/request_manager.py
quilt/context_base/user_manager.py
quilt/errors.py
quilt/extensions/__init__.py
quilt/extensions/calls.py
quilt/extensions/mask_errors.py
quilt/extensions/sentry.py
quilt/gql_utils/__init__.py
quilt/gql_utils/resolvers/__init__.py
quilt/gql_utils/resolvers/helpers.py
quilt/gql_utils/resolvers/hydrate.py
quilt/gql_utils/resolvers/logic.py
quilt/gql_utils/resolvers/models.py
quilt/gql_utils/resolvers/startup.py
quilt/gql_utils/strawberry_utils.py
quilt/helpers.py
quilt/logs.py
quilt/middlewares/__init__.py
quilt/middlewares/main.py
quilt/models/__init__.py
quilt/models/image.py
quilt/models/input_datetime.py
quilt/models/location/__init__.py
quilt/models/location/queries.py
quilt/models/phone_number.py
quilt/plugins/StrawberryFilters/default_filters.py
quilt/plugins/StrawberryFilters/generator.py
quilt/plugins/StrawberryFilters/logic.py
quilt/plugins/StrawberryFilters/mixins.py
quilt/scalars/__init__.py
quilt/scalars/phone_number.py
quilt/services/auth/__init__.py
quilt/services/auth/logic.py
quilt/services/auth/routes.py
quilt/services/auth/tests.py
quilt/types.py
quilt/utils.py
quilt/vendors/Cloudinary/__init__.py
quilt/vendors/Cloudinary/schemas.py
quilt/vendors/Firebase/__init__.py
quilt/vendors/GooglePlaces/__init__.py
quilt/vendors/GooglePlaces/main.py
quilt/vendors/GooglePlaces/tests/__init__.py
quilt/vendors/GooglePlaces/tests/example_response.json
quilt/vendors/IPInfo/__init__.py
quilt/vendors/Sentry/__init__.py
quilt/vendors/Sentry/context_managers.py
quilt/vendors/Sentry/decorators.py
quilt/vendors/__init__.py
quilt_py-0.10.5.dist-info/METADATA
quilt_py-0.10.5.dist-info/WHEEL
quilt_py-0.10.5.dist-info/RECORD
